rtl/basic/register.v
`timescale 1ns/1ps
module register #(parameter width = 8)(
    input wire clk ,
    input wire rst,
    input wire en,
    input wire [width-1:0] d,
    output reg  [width-1:0] q
);
always @(posedge clk) begin
    if (rst)
        q<= '0;
    else if (en)
        q<= d;
    
end
initial begin
    $dumpfile("verification/waveform/register.vcd");
    $dumpvars(0, register_tb);
end
endmodule

verification/testbench/register_tb.v
`timescale 1ns/1ps

module register_tb;

parameter width = 8;

reg clk;
reg rst;
reg en;
reg [width-1:0] d;

wire [width-1:0] q;

register #(
    .width(width)
) dut (
    .clk(clk),
    .rst(rst),
    .en(en),
    .d(d),
    .q(q)
);
always #5 clk = ~clk;

initial begin

    clk = 0;
    rst = 1;
    en  = 0;
    d   = 0;

    #10;

    rst = 0;

    en = 1;
    d = 8'hAA;

    #10;

    d = 8'h55;

    #10;

    en = 0;
    d = 8'hFF;

    #10;

    rst = 1;

    #10;

    $finish;

end

endmodule

verification/waveform/register.vcd
$date
	Wed Jul 15 13:37:53 2026
$end
$version
	Icarus Verilog
$end
$timescale
	1ps
$end
$scope module register_tb $end
$var wire 8 ! q [7:0] $end
$var parameter 32 " width $end
$var reg 1 # clk $end
$var reg 8 $ d [7:0] $end
$var reg 1 % en $end
$var reg 1 & rst $end
$scope module dut $end
$var wire 1 # clk $end
$var wire 8 ' d [7:0] $end
$var wire 1 % en $end
$var wire 1 & rst $end
$var parameter 32 ( width $end
$var reg 8 ) q [7:0] $end
$upscope $end
$upscope $end
$enddefinitions $end
$comment Show the parameter values. $end
$dumpall
b1000 (
b1000 "
$end
#0
$dumpvars
bx )
b0 '
1&
0%
b0 $
0#
bx !
$end
#5000
b0 !
b0 )
1#
#10000
0#
b10101010 $
b10101010 '
1%
0&
#15000
b10101010 !
b10101010 )
1#
#20000
0#
b1010101 $
b1010101 '
#25000
b1010101 !
b1010101 )
1#
#30000
0#
b11111111 $
b11111111 '
0%
#35000
1#
#40000
0#
1&
#45000
b0 !
b0 )
1#
