rtl/basic/accumulator.v
`timescale 1ns/1ps

module accumulator #(
    parameter WIDTH = 8
)(
    input wire clk,
    input wire rst,
    input wire en,
    input wire valid_in,

    input wire [(2*WIDTH)-1:0] data_in,

    output reg [(2*WIDTH)-1:0] sum
);

always @(posedge clk) begin

    if (rst)
        sum <= '0;

    else if (en && valid_in)
        sum <= sum + data_in;

end

endmodule

rtl/basic/multiplier.v
`timescale 1ns/1ps
module multiplier #(
    parameter WIDTH = 8
)(
    input  wire [WIDTH-1:0] a,
    input  wire [WIDTH-1:0] b,
    output wire [(2*WIDTH)-1:0] product
);
assign product = a * b;
endmodule

rtl/basic/mac.v
`timescale 1ns/1ps

module mac #(
    parameter WIDTH = 8
)(
    input wire clk,
    input wire rst,
    input wire en,

    input wire [WIDTH-1:0] a,
    input wire [WIDTH-1:0] b,

    output wire [(2*WIDTH)-1:0] sum,
    input valid_in
);

wire [(2*WIDTH)-1:0] product;

multiplier #(
    .WIDTH(WIDTH)
)
u_multiplier
(
    .a(a),
    .b(b),
    .product(product)
);

accumulator #(
    .WIDTH(WIDTH)
)
u_accumulator
(
    .clk(clk),
    .rst(rst),
    .en(en),
    .data_in(product),
    .sum(sum),
    .valid_in(valid_in)
);

endmodule

rtl/basic/pe_1.v
`timescale 1ns/1ps

module processing_element #(
    parameter WIDTH = 8
)(
    input  wire                     clk,
    input  wire                     rst,
    input  wire                     en,

    // Data valid signal
    input  wire                     valid_in,

    // Inputs
    input  wire [WIDTH-1:0]         activation_in,
    input  wire [WIDTH-1:0]         weight_in,

    // Forwarded outputs
    output reg  [WIDTH-1:0]         activation_out,
    output reg  [WIDTH-1:0]         weight_out,

    // Valid propagation
    output reg                      valid_out,

    // MAC result
    output wire [(2*WIDTH)-1:0]     partial_sum
);

    //----------------------------------------------------------
    // Internal Pipeline Registers
    //----------------------------------------------------------

    reg [WIDTH-1:0] activation_reg;
    reg [WIDTH-1:0] weight_reg;

    //----------------------------------------------------------
    // Input Pipeline Stage
    //----------------------------------------------------------

    always @(posedge clk) begin

        if (rst) begin

            activation_reg <= '0;
            weight_reg     <= '0;

            activation_out <= '0;
            weight_out     <= '0;

            valid_out      <= 1'b0;

        end

        else if (en ) begin

            // Register incoming data
            activation_reg <= activation_in;
            weight_reg     <= weight_in;

            // Forward data to neighbouring PE
            activation_out <= activation_in;
            weight_out     <= weight_in;

            // Propagate valid signal
            valid_out      <= valid_in;

        end

    end

    //----------------------------------------------------------
    // Multiply-Accumulate Unit
    //----------------------------------------------------------

    mac #(
        .WIDTH(WIDTH)
    )
    u_mac
    (
        .clk(clk),
        .rst(rst),
        .en(en),

        .a(activation_reg),
        .b(weight_reg),

        .sum(partial_sum),
        .valid_in(valid_in)
    );

endmodule

rtl/parameterized/systolic.v
`timescale 1ns/1ps

module systolic_array_2x2 #(
    parameter WIDTH = 8
)(
    input clk,
    input rst,
    input en,

    input valid_in,

    // Left side activations
    input [WIDTH-1:0] activation_in0,
    input [WIDTH-1:0] activation_in1,

    // Top side weights
    input [WIDTH-1:0] weight_in0,
    input [WIDTH-1:0] weight_in1,

    // Partial sums from each PE
    output [(2*WIDTH)-1:0] partial_sum00,
    output [(2*WIDTH)-1:0] partial_sum01,
    output [(2*WIDTH)-1:0] partial_sum10,
    output [(2*WIDTH)-1:0] partial_sum11,

    output valid_out
);

/////////////////////////////////////////////////////////////
// Internal activation wires
/////////////////////////////////////////////////////////////

wire [WIDTH-1:0] act_00_to_01;
wire [WIDTH-1:0] act_10_to_11;

/////////////////////////////////////////////////////////////
// Internal weight wires
/////////////////////////////////////////////////////////////

wire [WIDTH-1:0] wt_00_to_10;
wire [WIDTH-1:0] wt_01_to_11;

/////////////////////////////////////////////////////////////
// Internal valid wires
/////////////////////////////////////////////////////////////

wire valid00;
wire valid01;
wire valid10;
wire valid11;

/////////////////////////////////////////////////////////////
// PE00
/////////////////////////////////////////////////////////////

processing_element #(
    .WIDTH(WIDTH)
)
PE00
(
    .clk(clk),
    .rst(rst),
    .en(en),

    .valid_in(valid_in),

    .activation_in(activation_in0),
    .weight_in(weight_in0),

    .activation_out(act_00_to_01),
    .weight_out(wt_00_to_10),

    .valid_out(valid00),

    .partial_sum(partial_sum00)
);

/////////////////////////////////////////////////////////////
// PE01
/////////////////////////////////////////////////////////////

processing_element #(
    .WIDTH(WIDTH)
)
PE01
(
    .clk(clk),
    .rst(rst),
    .en(en),

    .valid_in(valid00),

    .activation_in(act_00_to_01),
    .weight_in(weight_in1),

    .activation_out(),
    .weight_out(wt_01_to_11),

    .valid_out(valid01),

    .partial_sum(partial_sum01)
);

/////////////////////////////////////////////////////////////
// PE10
/////////////////////////////////////////////////////////////

processing_element #(
    .WIDTH(WIDTH)
)
PE10
(
    .clk(clk),
    .rst(rst),
    .en(en),

    .valid_in(valid00),

    .activation_in(activation_in1),
    .weight_in(wt_00_to_10),

    .activation_out(act_10_to_11),
    .weight_out(),

    .valid_out(valid10),

    .partial_sum(partial_sum10)
);

/////////////////////////////////////////////////////////////
// PE11
/////////////////////////////////////////////////////////////

processing_element #(
    .WIDTH(WIDTH)
)
PE11
(
    .clk(clk),
    .rst(rst),
    .en(en),

    .valid_in(valid10),

    .activation_in(act_10_to_11),
    .weight_in(wt_01_to_11),

    .activation_out(),
    .weight_out(),

    .valid_out(valid11),

    .partial_sum(partial_sum11)
);

assign valid_out = valid11;

endmodule

verification/testbench/systolic_tb.v
`timescale 1ns/1ps

module systolic_array_2x2_tb;

parameter WIDTH = 8;

/////////////////////////////////////////////////////////
// Clock & Reset
/////////////////////////////////////////////////////////

reg clk;
reg rst;
reg en;
reg valid_in;

/////////////////////////////////////////////////////////
// Inputs
/////////////////////////////////////////////////////////

reg [WIDTH-1:0] activation_in0;
reg [WIDTH-1:0] activation_in1;

reg [WIDTH-1:0] weight_in0;
reg [WIDTH-1:0] weight_in1;

/////////////////////////////////////////////////////////
// Outputs
/////////////////////////////////////////////////////////

wire [(2*WIDTH)-1:0] partial_sum00;
wire [(2*WIDTH)-1:0] partial_sum01;
wire [(2*WIDTH)-1:0] partial_sum10;
wire [(2*WIDTH)-1:0] partial_sum11;

wire valid_out;

/////////////////////////////////////////////////////////
// DUT
/////////////////////////////////////////////////////////

systolic_array_2x2 #(
    .WIDTH(WIDTH)
)
dut
(
    .clk(clk),
    .rst(rst),
    .en(en),

    .valid_in(valid_in),

    .activation_in0(activation_in0),
    .activation_in1(activation_in1),

    .weight_in0(weight_in0),
    .weight_in1(weight_in1),

    .partial_sum00(partial_sum00),
    .partial_sum01(partial_sum01),
    .partial_sum10(partial_sum10),
    .partial_sum11(partial_sum11),

    .valid_out(valid_out)
);

/////////////////////////////////////////////////////////
// Clock Generation
/////////////////////////////////////////////////////////

always #5 clk = ~clk;

/////////////////////////////////////////////////////////
// Dumpfile
/////////////////////////////////////////////////////////

initial begin

    $dumpfile("./verification/waveform/systolic_array_2x2.vcd");
    $dumpvars(0,dut);

end

/////////////////////////////////////////////////////////
// Monitor
/////////////////////////////////////////////////////////

initial
begin

$monitor(
"Time=%0t | V=%b | A0=%d A1=%d | W0=%d W1=%d || SUM00=%d SUM01=%d SUM10=%d SUM11=%d",

$time,

valid_out,

activation_in0,
activation_in1,

weight_in0,
weight_in1,

partial_sum00,
partial_sum01,
partial_sum10,
partial_sum11

);

end

/////////////////////////////////////////////////////////
// Stimulus
/////////////////////////////////////////////////////////

initial
begin

clk = 0;
rst = 1;
en = 0;
valid_in = 0;

activation_in0 = 0;
activation_in1 = 0;

weight_in0 = 0;
weight_in1 = 0;

/////////////////////////////////////////////////////////
// Reset
/////////////////////////////////////////////////////////

#20;

rst = 0;
en = 1;
valid_in = 1;

/////////////////////////////////////////////////////////
// Cycle 1
/////////////////////////////////////////////////////////

activation_in0 = 2;
activation_in1 = 4;

weight_in0 = 3;
weight_in1 = 5;

#10;

/////////////////////////////////////////////////////////
// Cycle 2
/////////////////////////////////////////////////////////

activation_in0 = 6;
activation_in1 = 8;

weight_in0 = 7;
weight_in1 = 9;

#10;

/////////////////////////////////////////////////////////
// Cycle 3
/////////////////////////////////////////////////////////

activation_in0 = 10;
activation_in1 = 12;

weight_in0 = 11;
weight_in1 = 13;

#10;

/////////////////////////////////////////////////////////
// Stop Injecting
/////////////////////////////////////////////////////////

valid_in = 0;

#100;

$finish;

end

endmodule

verification/waveform/systolic_array_2x2.vcd
$date
	Wed Jul 22 11:37:17 2026
$end
$version
	Icarus Verilog
$end
$timescale
	1ps
$end
$scope module systolic_array_2x2_tb $end
$scope module dut $end
$var wire 8 ! activation_in0 [7:0] $end
$var wire 8 " activation_in1 [7:0] $end
$var wire 1 # clk $end
$var wire 1 $ en $end
$var wire 1 % rst $end
$var wire 1 & valid_in $end
$var wire 1 ' valid_out $end
$var wire 8 ( weight_in0 [7:0] $end
$var wire 8 ) weight_in1 [7:0] $end
$var wire 8 * wt_01_to_11 [7:0] $end
$var wire 8 + wt_00_to_10 [7:0] $end
$var wire 1 , valid11 $end
$var wire 1 - valid10 $end
$var wire 1 . valid01 $end
$var wire 1 / valid00 $end
$var wire 16 0 partial_sum11 [15:0] $end
$var wire 16 1 partial_sum10 [15:0] $end
$var wire 16 2 partial_sum01 [15:0] $end
$var wire 16 3 partial_sum00 [15:0] $end
$var wire 8 4 act_10_to_11 [7:0] $end
$var wire 8 5 act_00_to_01 [7:0] $end
$var parameter 32 6 WIDTH $end
$scope module PE00 $end
$var wire 8 7 activation_in [7:0] $end
$var wire 1 # clk $end
$var wire 1 $ en $end
$var wire 1 % rst $end
$var wire 1 & valid_in $end
$var wire 8 8 weight_in [7:0] $end
$var wire 16 9 partial_sum [15:0] $end
$var parameter 32 : WIDTH $end
$var reg 8 ; activation_out [7:0] $end
$var reg 8 < activation_reg [7:0] $end
$var reg 1 / valid_out $end
$var reg 8 = weight_out [7:0] $end
$var reg 8 > weight_reg [7:0] $end
$scope module u_mac $end
$var wire 8 ? a [7:0] $end
$var wire 8 @ b [7:0] $end
$var wire 1 # clk $end
$var wire 1 $ en $end
$var wire 1 % rst $end
$var wire 1 & valid_in $end
$var wire 16 A sum [15:0] $end
$var wire 16 B product [15:0] $end
$var parameter 32 C WIDTH $end
$scope module u_accumulator $end
$var wire 1 # clk $end
$var wire 1 $ en $end
$var wire 1 % rst $end
$var wire 1 & valid_in $end
$var wire 16 D data_in [15:0] $end
$var parameter 32 E WIDTH $end
$var reg 16 F sum [15:0] $end
$upscope $end
$scope module u_multiplier $end
$var wire 8 G a [7:0] $end
$var wire 8 H b [7:0] $end
$var wire 16 I product [15:0] $end
$var parameter 32 J WIDTH $end
$upscope $end
$upscope $end
$upscope $end
$scope module PE01 $end
$var wire 8 K activation_in [7:0] $end
$var wire 1 # clk $end
$var wire 1 $ en $end
$var wire 1 % rst $end
$var wire 1 / valid_in $end
$var wire 8 L weight_in [7:0] $end
$var wire 16 M partial_sum [15:0] $end
$var parameter 32 N WIDTH $end
$var reg 8 O activation_out [7:0] $end
$var reg 8 P activation_reg [7:0] $end
$var reg 1 . valid_out $end
$var reg 8 Q weight_out [7:0] $end
$var reg 8 R weight_reg [7:0] $end
$scope module u_mac $end
$var wire 8 S a [7:0] $end
$var wire 8 T b [7:0] $end
$var wire 1 # clk $end
$var wire 1 $ en $end
$var wire 1 % rst $end
$var wire 1 / valid_in $end
$var wire 16 U sum [15:0] $end
$var wire 16 V product [15:0] $end
$var parameter 32 W WIDTH $end
$scope module u_accumulator $end
$var wire 1 # clk $end
$var wire 1 $ en $end
$var wire 1 % rst $end
$var wire 1 / valid_in $end
$var wire 16 X data_in [15:0] $end
$var parameter 32 Y WIDTH $end
$var reg 16 Z sum [15:0] $end
$upscope $end
$scope module u_multiplier $end
$var wire 8 [ a [7:0] $end
$var wire 8 \ b [7:0] $end
$var wire 16 ] product [15:0] $end
$var parameter 32 ^ WIDTH $end
$upscope $end
$upscope $end
$upscope $end
$scope module PE10 $end
$var wire 8 _ activation_in [7:0] $end
$var wire 1 # clk $end
$var wire 1 $ en $end
$var wire 1 % rst $end
$var wire 1 / valid_in $end
$var wire 8 ` weight_in [7:0] $end
$var wire 16 a partial_sum [15:0] $end
$var parameter 32 b WIDTH $end
$var reg 8 c activation_out [7:0] $end
$var reg 8 d activation_reg [7:0] $end
$var reg 1 - valid_out $end
$var reg 8 e weight_out [7:0] $end
$var reg 8 f weight_reg [7:0] $end
$scope module u_mac $end
$var wire 8 g a [7:0] $end
$var wire 8 h b [7:0] $end
$var wire 1 # clk $end
$var wire 1 $ en $end
$var wire 1 % rst $end
$var wire 1 / valid_in $end
$var wire 16 i sum [15:0] $end
$var wire 16 j product [15:0] $end
$var parameter 32 k WIDTH $end
$scope module u_accumulator $end
$var wire 1 # clk $end
$var wire 1 $ en $end
$var wire 1 % rst $end
$var wire 1 / valid_in $end
$var wire 16 l data_in [15:0] $end
$var parameter 32 m WIDTH $end
$var reg 16 n sum [15:0] $end
$upscope $end
$scope module u_multiplier $end
$var wire 8 o a [7:0] $end
$var wire 8 p b [7:0] $end
$var wire 16 q product [15:0] $end
$var parameter 32 r WIDTH $end
$upscope $end
$upscope $end
$upscope $end
$scope module PE11 $end
$var wire 8 s activation_in [7:0] $end
$var wire 1 # clk $end
$var wire 1 $ en $end
$var wire 1 % rst $end
$var wire 1 - valid_in $end
$var wire 8 t weight_in [7:0] $end
$var wire 16 u partial_sum [15:0] $end
$var parameter 32 v WIDTH $end
$var reg 8 w activation_out [7:0] $end
$var reg 8 x activation_reg [7:0] $end
$var reg 1 , valid_out $end
$var reg 8 y weight_out [7:0] $end
$var reg 8 z weight_reg [7:0] $end
$scope module u_mac $end
$var wire 8 { a [7:0] $end
$var wire 8 | b [7:0] $end
$var wire 1 # clk $end
$var wire 1 $ en $end
$var wire 1 % rst $end
$var wire 1 - valid_in $end
$var wire 16 } sum [15:0] $end
$var wire 16 ~ product [15:0] $end
$var parameter 32 !" WIDTH $end
$scope module u_accumulator $end
$var wire 1 # clk $end
$var wire 1 $ en $end
$var wire 1 % rst $end
$var wire 1 - valid_in $end
$var wire 16 "" data_in [15:0] $end
$var parameter 32 #" WIDTH $end
$var reg 16 $" sum [15:0] $end
$upscope $end
$scope module u_multiplier $end
$var wire 8 %" a [7:0] $end
$var wire 8 &" b [7:0] $end
$var wire 16 '" product [15:0] $end
$var parameter 32 (" WIDTH $end
$upscope $end
$upscope $end
$upscope $end
$upscope $end
$upscope $end
$enddefinitions $end
$comment Show the parameter values. $end
$dumpall
b1000 ("
b1000 #"
b1000 !"
b1000 v
b1000 r
b1000 m
b1000 k
b1000 b
b1000 ^
b1000 Y
b1000 W
b1000 N
b1000 J
b1000 E
b1000 C
b1000 :
b1000 6
$end
#0
$dumpvars
bx '"
bx &"
bx %"
bx $"
bx ""
bx ~
bx }
bx |
bx {
bx z
bx y
bx x
bx w
bx u
bx t
bx s
bx q
bx p
bx o
bx n
bx l
bx j
bx i
bx h
bx g
bx f
bx e
bx d
bx c
bx a
bx `
b0 _
bx ]
bx \
bx [
bx Z
bx X
bx V
bx U
bx T
bx S
bx R
bx Q
bx P
bx O
bx M
b0 L
bx K
bx I
bx H
bx G
bx F
bx D
bx B
bx A
bx @
bx ?
bx >
bx =
bx <
bx ;
bx 9
b0 8
b0 7
bx 5
bx 4
bx 3
bx 2
bx 1
bx 0
x/
x.
x-
x,
bx +
bx *
b0 )
b0 (
x'
0&
1%
0$
0#
b0 "
b0 !
$end
#5000
b0 3
b0 9
b0 A
b0 F
0/
b0 +
b0 =
b0 `
b0 5
b0 ;
b0 K
b0 B
b0 D
b0 I
b0 >
b0 @
b0 H
b0 <
b0 ?
b0 G
b0 2
b0 M
b0 U
b0 Z
0.
b0 *
b0 Q
b0 t
b0 O
b0 V
b0 X
b0 ]
b0 R
b0 T
b0 \
b0 P
b0 S
b0 [
b0 1
b0 a
b0 i
b0 n
0-
b0 e
b0 4
b0 c
b0 s
b0 j
b0 l
b0 q
b0 f
b0 h
b0 p
b0 d
b0 g
b0 o
b0 0
b0 u
b0 }
b0 $"
0'
0,
b0 y
b0 w
b0 ~
b0 ""
b0 '"
b0 z
b0 |
b0 &"
b0 x
b0 {
b0 %"
1#
#10000
0#
#15000
1#
#20000
0#
b101 )
b101 L
b11 (
b11 8
b100 "
b100 _
b10 !
b10 7
1&
1$
0%
#25000
1/
b11 +
b11 =
b11 `
b10 5
b10 ;
b10 K
b110 B
b110 D
b110 I
b11 >
b11 @
b11 H
b10 <
b10 ?
b10 G
b101 *
b101 Q
b101 t
b101 R
b101 T
b101 \
b100 4
b100 c
b100 s
b100 d
b100 g
b100 o
1#
#30000
0#
b1001 )
b1001 L
b111 (
b111 8
b1000 "
b1000 _
b110 !
b110 7
#35000
b101 y
b100 w
b10100 ~
b10100 ""
b10100 '"
b101 z
b101 |
b101 &"
b100 x
b100 {
b100 %"
1-
b11 e
b1000 4
b1000 c
b1000 s
b11000 j
b11000 l
b11000 q
b11 f
b11 h
b11 p
b1000 d
b1000 g
b1000 o
1.
b1001 *
b1001 Q
b1001 t
b10 O
b1001 R
b1001 T
b1001 \
b10010 V
b10010 X
b10010 ]
b10 P
b10 S
b10 [
b111 +
b111 =
b111 `
b110 5
b110 ;
b110 K
b111 >
b111 @
b111 H
b101010 B
b101010 D
b101010 I
b110 <
b110 ?
b110 G
b110 3
b110 9
b110 A
b110 F
1#
#40000
0#
b1101 )
b1101 L
b1011 (
b1011 8
b1100 "
b1100 _
b1010 !
b1010 7
#45000
b110000 3
b110000 9
b110000 A
b110000 F
b1011 +
b1011 =
b1011 `
b1010 5
b1010 ;
b1010 K
b1011 >
b1011 @
b1011 H
b1101110 B
b1101110 D
b1101110 I
b1010 <
b1010 ?
b1010 G
b10010 2
b10010 M
b10010 U
b10010 Z
b1101 *
b1101 Q
b1101 t
b110 O
b1101 R
b1101 T
b1101 \
b1001110 V
b1001110 X
b1001110 ]
b110 P
b110 S
b110 [
b11000 1
b11000 a
b11000 i
b11000 n
b111 e
b1100 4
b1100 c
b1100 s
b111 f
b111 h
b111 p
b1010100 j
b1010100 l
b1010100 q
b1100 d
b1100 g
b1100 o
b10100 0
b10100 u
b10100 }
b10100 $"
1'
1,
b1001 y
b1000 w
b1001 z
b1001 |
b1001 &"
b1001000 ~
b1001000 ""
b1001000 '"
b1000 x
b1000 {
b1000 %"
1#
#50000
0#
0&
#55000
b1101 y
b1100 w
b1101 z
b1101 |
b1101 &"
b10011100 ~
b10011100 ""
b10011100 '"
b1100 x
b1100 {
b1100 %"
b1011100 0
b1011100 u
b1011100 }
b1011100 $"
b1011 e
b10000100 j
b10000100 l
b10000100 q
b1011 f
b1011 h
b1011 p
b1101100 1
b1101100 a
b1101100 i
b1101100 n
b1010 O
b10000010 V
b10000010 X
b10000010 ]
b1010 P
b1010 S
b1010 [
b1100000 2
b1100000 M
b1100000 U
b1100000 Z
0/
1#
#60000
0#
#65000
0.
0-
b11111000 0
b11111000 u
b11111000 }
b11111000 $"
1#
#70000
0#
#75000
0'
0,
1#
